README.rst
setup.py
Cnc25D.egg-info/PKG-INFO
Cnc25D.egg-info/SOURCES.txt
Cnc25D.egg-info/dependency_links.txt
Cnc25D.egg-info/requires.txt
Cnc25D.egg-info/top_level.txt
bin/cnc25d_example_generator.py
cnc25d/__init__.py
cnc25d/angles.py
cnc25d/axle_lid.py
cnc25d/bagel.py
cnc25d/bare_design.py
cnc25d/bell.py
cnc25d/bell_bagel_assembly.py
cnc25d/bell_outline.py
cnc25d/box_wood_frame.py
cnc25d/box_wood_frame_ng.py
cnc25d/box_wood_frame_outline.py
cnc25d/cnc25d_api.py
cnc25d/cnc25d_design.py
cnc25d/cnc_outline.py
cnc25d/crest.py
cnc25d/cross_cube.py
cnc25d/cross_cube_sub.py
cnc25d/design_help.py
cnc25d/design_output.py
cnc25d/display_backend.py
cnc25d/epicyclic_gearing.py
cnc25d/export_2d.py
cnc25d/gear_profile.py
cnc25d/gear_profile_outline.py
cnc25d/gearbar.py
cnc25d/gearring.py
cnc25d/gearwheel.py
cnc25d/gimbal.py
cnc25d/importing_freecad.py
cnc25d/motor_lid.py
cnc25d/outline_backends.py
cnc25d/positioning.py
cnc25d/small_geometry.py
cnc25d/split_gearwheel.py
cnc25d/tests/__init__.py
cnc25d/tests/axle_lid_macro.py
cnc25d/tests/bagel_macro.py
cnc25d/tests/bell_bagel_assembly_macro.py
cnc25d/tests/bell_macro.py
cnc25d/tests/box_wood_frame_macro.py
cnc25d/tests/bug_dxf_arc.py
cnc25d/tests/cnc25d_api_macro.py
cnc25d/tests/crest_macro.py
cnc25d/tests/cross_cube_macro.py
cnc25d/tests/epicyclic_gearing_macro.py
cnc25d/tests/gear_profile_macro.py
cnc25d/tests/gearbar_macro.py
cnc25d/tests/gearring_macro.py
cnc25d/tests/gearwheel_macro.py
cnc25d/tests/gimbal_macro.py
cnc25d/tests/importing_cnc25d.py
cnc25d/tests/juergen_four_gearwheel_test.py
cnc25d/tests/motor_lid_macro.py
cnc25d/tests/simple_cnc25d_api_macro.py
cnc25d/tests/split_gearwheel_macro.py