Metadata-Version: 1.0
Name: Cnc25D
Version: 0.1.10
Summary: CAD library for 2.5D parts (including gears) using svgwrite, dxfwrite or FreeCAD as backend
Home-page: http://pypi.python.org/pypi/Cnc25D/
Author: charlyoleg
Author-email: charlyoleg@fabfolk.com
License: LICENSE.txt
Keywords: CNC 2.5D FreeCAD 3D gear
Platform: UNKNOWN
